tssenrich/__init__.py
tssenrich/clean_bed12.py
tssenrich/hg19.bed12.bed.gz
tssenrich/hg19.full.bed12.bed.gz
tssenrich/hg19.refFlat.sql
tssenrich/hg19.refFlat.txt.gz
tssenrich/hg38.bed12.bed.gz
tssenrich/hg38.full.bed12.bed.gz
tssenrich/hg38.refFlat.sql
tssenrich/hg38.refFlat.txt.gz
tssenrich/mm10.bed12.bed.gz
tssenrich/mm10.full.bed12.bed.gz
tssenrich/mm10.refFlat.sql
tssenrich/mm10.refFlat.txt.gz
tssenrich/tssenrich.py
tssenrich-1.4.6.dist-info/LICENSE
tssenrich-1.4.6.dist-info/METADATA
tssenrich-1.4.6.dist-info/WHEEL
tssenrich-1.4.6.dist-info/entry_points.txt
tssenrich-1.4.6.dist-info/top_level.txt
tssenrich-1.4.6.dist-info/RECORD
