Metadata-Version: 2.1
Name: tssenrich
Version: 1.4.6
Summary: Calculate TSS enrichment for ATAC-seq data
Home-page: https://gitlab.com/aaylward/tssenrich
Author: Anthony Aylward
Author-email: aaylward@salk.edu
License: UNKNOWN
Platform: UNKNOWN
Classifier: Programming Language :: Python :: 3
Classifier: License :: OSI Approved :: MIT License
Classifier: Operating System :: OS Independent
License-File: LICENSE
Requires-Dist: pybedtools
